[
  {
    "trainerName": "John Smith",
    "profileImage": "https://i.ibb.co/hdDbYWb/coach2.jpg",
    "experience": "10+ years",
    "email": "john@example.com",
    "age": 35,
    "availableTimeWeek": "Monday, Wednesday, Friday",
    "availableTimeDay": "Morning, Afternoon, Evening",
    "slot":[
     { 
       "availableTime": "9 AM - 10 AM,"
      },
     { 
       "availableTime": "11 AM - 12 AM"
      },
     { 
       "availableTime": "1 AM - 2 AM"
      }
    ]
  },
  {
    "trainerName": "Emily Johnson",
    "profileImage": "https://i.ibb.co/PmdCyQf/coach1.jpg",
    "experience": "2 years",
    "availableTimeSlot": "8 AM - 11 AM, 5 PM - 8 PM",
    "email": "emily@example.com",
    "age": 28,
    "availableTimeWeek": "Tuesday, Thursday, Saturday",
    "availableTimeDay": "Morning, Evening",
    "slot":[
      { 
        "availableTime": "9 AM - 10 AM,"
       },
      { 
        "availableTime": "11 AM - 12 AM"
       },
      { 
        "availableTime": "1 AM - 2 AM"
       },
      { 
        "availableTime": "1 AM - 2 AM"
       }
     ]
  },
  {
    "trainerName": "Michael Brown",
    "profileImage": "https://i.ibb.co/0fqTvCt/trainer1.jpg",
    "experience": "8 years",
    "availableTimeSlot": "6 AM - 10 AM, 4 PM - 9 PM",
    "email": "michael@example.com",
    "age": 42,
    "availableTimeWeek": "Monday - Saturday",
    "availableTimeDay": "Morning, Evening",
    "slot":[
      { 
        "availableTime": "9 AM - 10 AM,"
       },
      { 
        "availableTime": "11 AM - 12 AM"
       },
      { 
        "availableTime": "1 AM - 2 AM"
       },
      { 
        "availableTime": "1 AM - 2 AM"
       },
      { 
        "availableTime": "1 AM - 2 AM"
       }
     ]
  },
  {
    "trainerName": "Sophia Garcia",
    "profileImage": "https://i.ibb.co/n1v9Gy9/trainer2.jpg",
    "experience": "5 years",
    "availableTimeSlot": "7 AM - 12 PM, 2 PM - 6 PM",
    "email": "sophia@example.com",
    "age": 30,
    "availableTimeWeek": "Monday, Wednesday, Friday, Sunday",
    "availableTimeDay": "Morning, Afternoon",
    "slot":[
      { 
        "availableTime": "9 AM - 10 AM,"
       },
      { 
        "availableTime": "11 AM - 12 AM"
       }
     ]
  },
  {
    "trainerName": "David Martinez",
    "profileImage": "https://i.ibb.co/Qn5R4WQ/trainer3.jpg",
    "experience": "6 years",
    "availableTimeSlot": "10 AM - 1 PM, 4 PM - 8 PM",
    "email": "david@example.com",
    "age": 33,
    "availableTimeWeek": "Tuesday, Thursday, Saturday",
    "availableTimeDay": "Morning, Evening",
    "slot":[
      { 
        "availableTime": "9 AM - 10 AM,"
       },
      { 
        "availableTime": "11 AM - 12 AM"
       },
      { 
        "availableTime": "1 AM - 2 AM"
       },
      { 
        "availableTime": "1 AM - 2 AM"
       },
      { 
        "availableTime": "1 AM - 2 AM"
       },
      { 
        "availableTime": "1 AM - 2 AM"
       }
     ]
  },
  {
    "trainerName": "Olivia Wilson",
    "profileImage": "https://i.ibb.co/Lzbw9tF/trainer4.jpg",
    "experience": "3 years",
    "availableTimeSlot": "6-9",
    "email": "olivia@example.com",
    "age": 29,
    "availableTimeWeek": "Monday - Saturday",
    "availableTimeDay": "Morning, Evening",
    "slot":[
      { 
        "availableTime": "9 AM - 10 AM,"
       },
      { 
        "availableTime": "11 AM - 12 AM"
       },
      { 
        "availableTime": "1 AM - 2 AM"
       },
      { 
        "availableTime": "1 AM - 2 AM"
       }
     ]
  }
]
